bsl/__init__.py
bsl/_version.py
bsl/commands/__init__.py
bsl/commands/bsl_stream_player.py
bsl/commands/bsl_stream_recorder.py
bsl/commands/bsl_stream_viewer.py
bsl/commands/main.py
bsl/commands/sys_info.py
bsl/datasets/__init__.py
bsl/datasets/_fetching.py
bsl/datasets/eeg_auditory_stimuli.py
bsl/datasets/eeg_resting_state.py
bsl/datasets/eeg_resting_state_short.py
bsl/datasets/trigger_def.py
bsl/lsl/__init__.py
bsl/lsl/constants.py
bsl/lsl/functions.py
bsl/lsl/load_liblsl.py
bsl/lsl/stream_info.py
bsl/lsl/stream_inlet.py
bsl/lsl/stream_outlet.py
bsl/lsl/utils.py
bsl/lsl/lib/liblsl-1.16.0-20.04_amd64.so
bsl/lsl/lib/liblsl-1.16.0-22.04_amd64.so
bsl/lsl/lib/liblsl-1.16.0-OSX_amd64.dylib
bsl/lsl/lib/liblsl-1.16.0-OSX_arm64.dylib
bsl/lsl/lib/liblsl-1.16.0-Win_amd64.dll
bsl/lsl/lib/liblsl-1.16.0-Win_i386.dll
bsl/stream_player/__init__.py
bsl/stream_player/stream_player.py
bsl/stream_receiver/__init__.py
bsl/stream_receiver/_buffer.py
bsl/stream_receiver/_stream.py
bsl/stream_receiver/stream_receiver.py
bsl/stream_recorder/__init__.py
bsl/stream_recorder/stream_recorder.py
bsl/stream_viewer/__init__.py
bsl/stream_viewer/stream_viewer.py
bsl/stream_viewer/backends/__init__.py
bsl/stream_viewer/backends/_backend.py
bsl/stream_viewer/backends/pyqtgraph.py
bsl/stream_viewer/control_gui/__init__.py
bsl/stream_viewer/control_gui/_control.py
bsl/stream_viewer/control_gui/_ui_control.py
bsl/stream_viewer/control_gui/control_eeg.py
bsl/stream_viewer/control_gui/settings/settings_scope_eeg.ini
bsl/stream_viewer/scope/__init__.py
bsl/stream_viewer/scope/_scope.py
bsl/stream_viewer/scope/scope_eeg.py
bsl/triggers/__init__.py
bsl/triggers/_base.py
bsl/triggers/lsl.py
bsl/triggers/mock.py
bsl/triggers/parallel.py
bsl/triggers/trigger_def.py
bsl/triggers/io/__init__.py
bsl/triggers/io/_dlportio.py
bsl/triggers/io/_inpout.py
bsl/triggers/io/_linux.py
bsl/utils/__init__.py
bsl/utils/_checks.py
bsl/utils/_docs.py
bsl/utils/_exceptions.py
bsl/utils/_fixes.py
bsl/utils/_imports.py
bsl-0.6.4.dist-info/LICENSE
bsl-0.6.4.dist-info/METADATA
bsl-0.6.4.dist-info/WHEEL
bsl-0.6.4.dist-info/entry_points.txt
bsl-0.6.4.dist-info/top_level.txt
bsl-0.6.4.dist-info/RECORD
