Metadata-Version: 2.1
Name: bsl
Version: 0.6.4
Summary: Real-time framework for online neuroscience research through LSL-compatible devices.
Author-email: Mathieu Scheltienne <mathieu.scheltienne@fcbg.ch>, Arnaud Desvachez <arnaud.desvachez@gmail.com>, Kyuhwa Lee <lee.kyuh@gmail.com>
Maintainer-email: Mathieu Scheltienne <mathieu.scheltienne@fcbg.ch>
License: MIT License
Project-URL: homepage, https://bsl-tools.github.io/
Project-URL: documentation, https://bsl-tools.github.io/
Project-URL: source, https://github.com/fcbg-hnp-meeg/bsl
Project-URL: tracker, https://github.com/fcbg-hnp-meeg/bsl/issues
Keywords: python,neuroscience,neuroimaging,EEG,LSL,real-time,brain
Classifier: Operating System :: Microsoft :: Windows
Classifier: Operating System :: Unix
Classifier: Operating System :: MacOS
Classifier: Programming Language :: Python :: 3 :: Only
Classifier: Programming Language :: Python :: 3.8
Classifier: Programming Language :: Python :: 3.9
Classifier: Programming Language :: Python :: 3.10
Classifier: Programming Language :: Python :: 3.11
Classifier: Natural Language :: English
Classifier: License :: OSI Approved :: BSD License
Classifier: Intended Audience :: Science/Research
Classifier: Intended Audience :: Developers
Classifier: Topic :: Software Development
Classifier: Topic :: Scientific/Engineering
Requires-Python: >=3.8
License-File: LICENSE
Requires-Dist: mne >=1.1.1
Requires-Dist: numpy >=1.21
Requires-Dist: packaging
Requires-Dist: psutil
Requires-Dist: pyqtgraph
Requires-Dist: PyQt5
Requires-Dist: scipy
Requires-Dist: distro ; sys_platform == "linux"
Provides-Extra: all
Requires-Dist: bsl[build] ; extra == 'all'
Requires-Dist: bsl[doc] ; extra == 'all'
Requires-Dist: bsl[triggers] ; extra == 'all'
Requires-Dist: bsl[style] ; extra == 'all'
Requires-Dist: bsl[test] ; extra == 'all'
Provides-Extra: build
Requires-Dist: build ; extra == 'build'
Requires-Dist: twine ; extra == 'build'
Provides-Extra: doc
Requires-Dist: furo ; extra == 'doc'
Requires-Dist: matplotlib ; extra == 'doc'
Requires-Dist: memory-profiler ; extra == 'doc'
Requires-Dist: numpydoc ; extra == 'doc'
Requires-Dist: sphinx ; extra == 'doc'
Requires-Dist: sphinxcontrib-bibtex ; extra == 'doc'
Requires-Dist: sphinx-copybutton ; extra == 'doc'
Requires-Dist: sphinx-design ; extra == 'doc'
Requires-Dist: sphinx-gallery ; extra == 'doc'
Requires-Dist: sphinx-issues ; extra == 'doc'
Provides-Extra: full
Requires-Dist: bsl[all] ; extra == 'full'
Provides-Extra: style
Requires-Dist: bibclean ; extra == 'style'
Requires-Dist: black ; extra == 'style'
Requires-Dist: codespell ; extra == 'style'
Requires-Dist: isort ; extra == 'style'
Requires-Dist: pydocstyle[toml] ; extra == 'style'
Requires-Dist: ruff ; extra == 'style'
Provides-Extra: test
Requires-Dist: bsl[triggers] ; extra == 'test'
Requires-Dist: pytest ; extra == 'test'
Requires-Dist: pytest-cov ; extra == 'test'
Requires-Dist: pytest-timeout ; extra == 'test'
Requires-Dist: requests ; extra == 'test'
Provides-Extra: triggers
Requires-Dist: pyserial ; extra == 'triggers'
Requires-Dist: pyparallel ; (sys_platform == "linux") and extra == 'triggers'
